lpa/input/__init__.py
lpa/input/analyze.py
lpa/input/boundaries.py
lpa/input/data.py
lpa/input/geometries.py
lpa/input/maps.py
lpa/input/models.py
lpa/input/notation.py
lpa/input/overlap.py
lpa/input/parallel.py
lpa/input/sets.py
lpa/input/data/cc.dat
lpa/input/data/cs.dat
lpa_input-1.2.9.dist-info/LICENSE.txt
lpa_input-1.2.9.dist-info/METADATA
lpa_input-1.2.9.dist-info/WHEEL
lpa_input-1.2.9.dist-info/top_level.txt
lpa_input-1.2.9.dist-info/RECORD
