Metadata-Version: 2.1
Name: lpa-input
Version: 1.2.9
Summary: Tools for the generation and analysis of dislocation distributions.
Home-page: https://github.com/DunstanBecht/lpa-input
Author: Dunstan Becht
Author-email: dunstan@becht.network
License: UNKNOWN
Project-URL: Bug Tracker, https://github.com/DunstanBecht/lpa-input/issues
Platform: UNKNOWN
Classifier: Programming Language :: Python :: 3
Classifier: License :: CC0 1.0 Universal (CC0 1.0) Public Domain Dedication
Classifier: Operating System :: OS Independent
Classifier: Topic :: Scientific/Engineering :: Physics
Classifier: Topic :: System :: Clustering
License-File: LICENSE.txt
Requires-Dist: numpy
Requires-Dist: matplotlib
Requires-Dist: beartype
Requires-Dist: scipy
